hascal/__init__.py
hascal/hascal.py
hascal/core/__init__.py
hascal/core/h_builder.py
hascal/core/h_compiler.py
hascal/core/h_error.py
hascal/core/h_help.py
hascal/core/h_import.py
hascal/core/h_lexer.py
hascal/core/h_parser.py
hascal/core/sly/__init__.py
hascal/core/sly/ast.py
hascal/core/sly/docparse.py
hascal/core/sly/lex.py
hascal/core/sly/yacc.py
hascal/hlib/conv.has
hascal/hlib/datetime.has
hascal/hlib/file.has
hascal/hlib/functional.has
hascal/hlib/http.has
hascal/hlib/ini.has
hascal/hlib/libtcc.has
hascal/hlib/math.has
hascal/hlib/os.has
hascal/hlib/path.has
hascal/hlib/random.has
hascal/hlib/regex.has
hascal/hlib/strings.has
hascal/hlib/termcolor.has
hascal/hlib/time.has
hascal/hlib/crypto/sha256.has
hascal/hlib/js/http.js
hascal/hlib/js/std.js
hascal/hlib/libcpp/LICENSE-argparse
hascal/hlib/libcpp/LICENSE-cwalk
hascal/hlib/libcpp/argparse.cc
hascal/hlib/libcpp/argparse.hpp
hascal/hlib/libcpp/conv.cc
hascal/hlib/libcpp/conv.hpp
hascal/hlib/libcpp/cwalk.cc
hascal/hlib/libcpp/cwalk.hpp
hascal/hlib/libcpp/datetime.cc
hascal/hlib/libcpp/datetime.hpp
hascal/hlib/libcpp/http.cc
hascal/hlib/libcpp/http.hpp
hascal/hlib/libcpp/http.ld
hascal/hlib/libcpp/http.wld
hascal/hlib/libcpp/ini.cc
hascal/hlib/libcpp/ini.hpp
hascal/hlib/libcpp/math.cc
hascal/hlib/libcpp/math.hpp
hascal/hlib/libcpp/random.cc
hascal/hlib/libcpp/random.hpp
hascal/hlib/libcpp/sha256.cc
hascal/hlib/libcpp/sha256.hpp
hascal/hlib/libcpp/std.cc
hascal/hlib/libcpp/std.hpp
hascal/hlib/libcpp/termcolor.cc
hascal/hlib/libcpp/termcolor.hpp
hascal-1.3.8.dist-info/LICENSE
hascal-1.3.8.dist-info/METADATA
hascal-1.3.8.dist-info/WHEEL
hascal-1.3.8.dist-info/entry_points.txt
hascal-1.3.8.dist-info/top_level.txt
hascal-1.3.8.dist-info/RECORD
